alpineer/__init__.py
alpineer/data_utils.py
alpineer/image_utils.py
alpineer/io_utils.py
alpineer/load_utils.py
alpineer/misc_utils.py
alpineer/py.typed
alpineer/settings.py
alpineer/test_utils.py
alpineer/tiff_utils.py
alpineer-0.1.13.dist-info/LICENSE
alpineer-0.1.13.dist-info/METADATA
alpineer-0.1.13.dist-info/WHEEL
alpineer-0.1.13.dist-info/RECORD
