Metadata-Version: 2.3
Name: alpineer
Version: 0.1.13
Summary: Toolbox for Multiplexed Imaging. Contains scripts and little tools which are used throughout ark-analysis, mibi-bin-tools, and toffy.
License: Modified Apache 2.0
Author: Noah Frey Greenwald
Author-email: nfgreen@stanford.edu
Requires-Python: >=3.9,<3.13
Classifier: License :: Other/Proprietary License
Classifier: Programming Language :: Python :: 3
Classifier: Programming Language :: Python :: 3.9
Classifier: Programming Language :: Python :: 3.10
Classifier: Programming Language :: Python :: 3.11
Classifier: Programming Language :: Python :: 3.12
Requires-Dist: charset-normalizer (>=2.1.1,<3.0.0)
Requires-Dist: imageio (>=2.3.0,<3.0.0)
Requires-Dist: matplotlib (>=3,<4)
Requires-Dist: natsort (>=8,<9)
Requires-Dist: numpy (==1.*)
Requires-Dist: pillow
Requires-Dist: scikit-image (==0.*)
Requires-Dist: tifffile
Requires-Dist: xarray
Requires-Dist: xmltodict (>=0.13.0,<0.14.0)
Project-URL: Documentation, https://alpineer.readthedocs.io
Project-URL: Homepage, https://github.com/angelolab/alpineer
Project-URL: Repository, https://github.com/angelolab/alpineer
